{
    "prepare_queue": {
        "installed": [],
        "uninstalled": []
    },
    "config_munge": {
        "files": {
            "res/xml/config.xml": {
                "parents": {
                    "/*": [
                        {
                            "xml": "<feature name=\"Sms\"><param name=\"android-package\" value=\"com.cordova.plugins.sms.Sms\" /></feature>",
                            "count": 1
                        },
                        {
                            "xml": "<feature name=\"Whitelist\"><param name=\"android-package\" value=\"org.apache.cordova.whitelist.WhitelistPlugin\" /><param name=\"onload\" value=\"true\" /></feature>",
                            "count": 1
                        }
                    ]
                }
            },
            "AndroidManifest.xml": {
                "parents": {
                    "/manifest": [
                        {
                            "xml": "<uses-permission android:name=\"android.permission.SEND_SMS\" />",
                            "count": 1
                        },
                        {
                            "xml": "<uses-permission android:name=\"android.permission.READ_PHONE_STATE\" />",
                            "count": 1
                        },
                        {
                            "xml": "<uses-feature android:name=\"android.hardware.telephony\" android:required=\"false\" />",
                            "count": 1
                        }
                    ]
                }
            }
        }
    },
    "installed_plugins": {
        "com.cordova.plugins.sms": {
            "PACKAGE_NAME": "com.ionicframework.swetha907547"
        },
        "cordova-plugin-whitelist": {
            "PACKAGE_NAME": "com.ionicframework.swetha907547"
        }
    },
    "dependent_plugins": {},
    "modules": [
        {
            "file": "plugins/com.cordova.plugins.sms/www/sms.js",
            "id": "com.cordova.plugins.sms.Sms",
            "clobbers": [
                "window.sms"
            ]
        },
        {
            "file": "plugins/cordova-plugin-whitelist/whitelist.js",
            "id": "cordova-plugin-whitelist.whitelist",
            "runs": true
        }
    ],
    "plugin_metadata": {
        "com.cordova.plugins.sms": "0.1.9",
        "cordova-plugin-whitelist": "1.2.1"
    }
}